pelican_embedly/__init__.py
pelican_embedly/card_rst.py
pelican_embedly-0.2.0.dist-info/DESCRIPTION.rst
pelican_embedly-0.2.0.dist-info/METADATA
pelican_embedly-0.2.0.dist-info/RECORD
pelican_embedly-0.2.0.dist-info/WHEEL
pelican_embedly-0.2.0.dist-info/entry_points.txt
pelican_embedly-0.2.0.dist-info/metadata.json
pelican_embedly-0.2.0.dist-info/top_level.txt
