Metadata-Version: 2.0
Name: pelican-embedly
Version: 0.2.0
Summary: embed.ly cards for Pelican blog
Home-page: https://github.com/euri10/python-pelican_embedly
Author: benoit barthelet
Author-email: benoit.barthelet@gmail.com
License: BSD license
Platform: UNKNOWN
Classifier: Development Status :: 5 - Production/Stable
Classifier: Intended Audience :: Developers
Classifier: License :: OSI Approved :: BSD License
Classifier: Operating System :: Unix
Classifier: Operating System :: POSIX
Classifier: Operating System :: Microsoft :: Windows
Classifier: Programming Language :: Python
Classifier: Programming Language :: Python :: 2.7
Classifier: Programming Language :: Python :: 3.5
Classifier: Programming Language :: Python :: Implementation :: PyPy
Classifier: Topic :: Utilities
Requires-Dist: pelican
